pylodge/__init__.py
pylodge/pylodge.py
pylodge-0.2.9.dist-info/DESCRIPTION.rst
pylodge-0.2.9.dist-info/METADATA
pylodge-0.2.9.dist-info/metadata.json
pylodge-0.2.9.dist-info/RECORD
pylodge-0.2.9.dist-info/top_level.txt
pylodge-0.2.9.dist-info/WHEEL
