Metadata-Version: 2.0
Name: pylodge
Version: 0.2.9
Summary: Test Automation framework for TestLodge
Home-page: https://github.com/gettalent/pylodge
Author: Ashwin Kondapalli
Author-email: ashwin@gettalent.com
License: MIT
Keywords: TestLodge,test automation,pylodge
Platform: UNKNOWN
Classifier: Development Status :: 5 - Production/Stable
Classifier: Intended Audience :: Developers
Classifier: Topic :: Software Development :: Quality Assurance
Classifier: Programming Language :: Python
Classifier: License :: OSI Approved :: MIT License
Requires-Dist: requests
